bigquery_ml_utils/__init__.py
bigquery_ml_utils/model_generator/__init__.py
bigquery_ml_utils/model_generator/text_embedding_generator.py
bigquery_ml_utils/inference/__init__.py
bigquery_ml_utils/inference/transform_predictor/__init__.py
bigquery_ml_utils/inference/transform_predictor/predictor.py
bigquery_ml_utils/inference/xgboost_predictor/__init__.py
bigquery_ml_utils/inference/xgboost_predictor/predictor.py
bigquery_ml_utils/tensorflow_ops/_time_ops.so
bigquery_ml_utils/tensorflow_ops/__init__.py
bigquery_ml_utils/tensorflow_ops/_timestamp_ops.so
bigquery_ml_utils/tensorflow_ops/_datetime_ops.so
bigquery_ml_utils/tensorflow_ops/datetime_ops.py
bigquery_ml_utils/tensorflow_ops/_date_ops.so
bigquery_ml_utils/tensorflow_ops/date_ops.py
bigquery_ml_utils/tensorflow_ops/time_ops.py
bigquery_ml_utils/tensorflow_ops/timestamp_ops.py
bigquery_ml_utils/tensorflow_ops/load_module.py
bigquery_ml_utils-1.3.0.dist-info/LICENSE
bigquery_ml_utils-1.3.0.dist-info/WHEEL
bigquery_ml_utils-1.3.0.dist-info/METADATA
bigquery_ml_utils-1.3.0.dist-info/top_level.txt
bigquery_ml_utils-1.3.0.dist-info/RECORD
