Metadata-Version: 2.1
Name: bigquery-ml-utils
Version: 1.3.0
Summary: BigQuery ML Utils
Home-page: https://github.com/GoogleCloudPlatform/bigquery-ml-utils
Author: Google Inc.
Author-email: no-reply@google.com
License: Apache 2.0
Keywords: bqml utils
License-File: LICENSE
Requires-Dist: absl-py
Requires-Dist: xgboost
Requires-Dist: numpy
Requires-Dist: tensorflow ~=2.11.0
Requires-Dist: tensorflow-hub
Requires-Dist: tensorflow-text
Requires-Dist: tzdata
